TracTicketGraph-1.0.6.dist-info/DESCRIPTION.rst
TracTicketGraph-1.0.6.dist-info/METADATA
TracTicketGraph-1.0.6.dist-info/RECORD
TracTicketGraph-1.0.6.dist-info/WHEEL
TracTicketGraph-1.0.6.dist-info/entry_points.txt
TracTicketGraph-1.0.6.dist-info/metadata.json
TracTicketGraph-1.0.6.dist-info/top_level.txt
ticketgraph/__init__.py
ticketgraph/ticketgraph.py
ticketgraph/htdocs/flot-0.8.3.zip
ticketgraph/htdocs/jquery.flot.min.js
ticketgraph/htdocs/jquery.flot.stack.min.js
ticketgraph/htdocs/jquery.flot.time.min.js
ticketgraph/htdocs/ticketgraph.js
ticketgraph/templates/ticketgraph.html
