Metadata-Version: 2.0
Name: TracTicketGraph
Version: 1.0.6
Summary: Graphs Trac tickets over time
Home-page: https://github.com/trac-hacks/TracTicketGraph
Author: Colin Snover
Author-email: tracplugins@zetafleet.com
License: MIT
Keywords: trac plugin ticket statistics graph
Platform: UNKNOWN
Classifier: Framework :: Trac
Requires-Dist: Trac
